web_fractal/__init__.py
web_fractal/building_utils.py
web_fractal/db.py
web_fractal/dtos.py
web_fractal/env_helpers.py
web_fractal/middlewares.py
web_fractal/types.py
web_fractal/utils.py
web_fractal/cli/__init__.py
web_fractal/cli/base.py
web_fractal/cli/interfaces.py
web_fractal/django/__init__.py
web_fractal/django/utils.py
web_fractal/http/__init__.py
web_fractal/http/interfaces.py
web_fractal/http/types_.py
web_fractal-0.0.1.dist-info/METADATA
web_fractal-0.0.1.dist-info/WHEEL
web_fractal-0.0.1.dist-info/top_level.txt
web_fractal-0.0.1.dist-info/RECORD
