Metadata-Version: 2.4
Name: web_fractal
Version: 0.0.1
Summary: reborn to kill
Author-email: Aleksandr <vkusnisaharok@gmail.com>
Requires-Python: >=3.12
